{"version": "perception-2025-08-10", "image": {"w": 1440, "h": 1097, "hash": "sha256-11de97e99930637918e858f096e77989db31f31411cd1c2bfcb387e2a5fc3d28"}, "texts": [{"id": "texts.t0", "text": "LT leetify", "bbox": [27, 12, 104, 21], "conf": 0.6501322686672211, "approxSizePx": 15}, {"id": "texts.t1", "text": "Q Player comparison - Faceit nickname , Steam id or Steam profile link", "bbox": [203, 17, 375, 10], "conf": 0.9368645502970769, "approxSizePx": 7}, {"id": "texts.t2", "text": "GET PRO", "bbox": [1152, 17, 43, 7], "conf": 0.9843536913394928, "approxSizePx": 5}, {"id": "texts.t3", "text": "nte", "bbox": [1319, 17, 17, 8], "conf": 0.9712020754814148, "approxSizePx": 6}, {"id": "texts.t4", "text": "My Data", "bbox": [21, 56, 44, 9], "conf": 0.9736116230487823, "approxSizePx": 6}, {"id": "texts.t5", "text": "VICTORY 16 : 9", "bbox": [211, 97, 259, 26], "conf": 0.9849640130996704, "approxSizePx": 18}, {"id": "texts.t6", "text": "Home", "bbox": [46, 99, 31, 10], "conf": 0.9883285164833069, "approxSizePx": 7}, {"id": "texts.t7", "text": "M My Stats", "bbox": [25, 143, 66, 13], "conf": 0.8191247582435608, "approxSizePx": 9}, {"id": "texts.t8", "text": "Highlights / 4▾", "bbox": [937, 166, 126, 18], "conf": 0.7269207835197449, "approxSizePx": 13}, {"id": "texts.t9", "text": "Ancient / MR30", "bbox": [244, 169, 109, 10], "conf": 0.91940305630366, "approxSizePx": 7}, {"id": "texts.t10", "text": "05 Dec 2022 17:29 pm", "bbox": [435, 170, 148, 11], "conf": 0.9822207689285278, "approxSizePx": 8}, {"id": "texts.t11", "text": "Achievements / +3 ▼", "bbox": [693, 170, 159, 10], "conf": 0.7905981242656708, "approxSizePx": 7}, {"id": "texts.t12", "text": "Focus Areas", "bbox": [45, 186, 64, 11], "conf": 0.9554665684700012, "approxSizePx": 8}, {"id": "texts.t13", "text": "Maps", "bbox": [46, 232, 29, 10], "conf": 0.9307577610015869, "approxSizePx": 7}, {"id": "texts.t14", "text": "Glock ACE on Inferno Processing ( 2 minutes ) ..", "bbox": [728, 248, 124, 26], "conf": 0.9341070413589477, "approxSizePx": 18}, {"id": "texts.t15", "text": "AK - 47 ACE on Dust2 Processing ( 2minutes ) ..", "bbox": [239, 249, 120, 25], "conf": 0.9191311543638055, "approxSizePx": 18}, {"id": "texts.t16", "text": "AK - 47 ACE on Dust2 Processing ( 2 minutes ) ..", "bbox": [482, 249, 119, 25], "conf": 0.9607439587513605, "approxSizePx": 18}, {"id": "texts.t17", "text": "→ Aim", "bbox": [25, 275, 42, 11], "conf": 0.6391306966543198, "approxSizePx": 8}, {"id": "texts.t18", "text": "Utility", "bbox": [46, 320, 29, 10], "conf": 0.9683778882026672, "approxSizePx": 7}, {"id": "texts.t19", "text": "ALLSTAR", "bbox": [206, 353, 34, 9], "conf": 0.9860658645629883, "approxSizePx": 6}, {"id": "texts.t20", "text": "ALLSTAR", "bbox": [449, 353, 34, 9], "conf": 0.9889469146728516, "approxSizePx": 6}, {"id": "texts.t21", "text": "ALLSTAR", "bbox": [696, 353, 34, 9], "conf": 0.9886699318885803, "approxSizePx": 6}, {"id": "texts.t22", "text": "Matches", "bbox": [46, 362, 44, 11], "conf": 0.9842892289161682, "approxSizePx": 8}, {"id": "texts.t23", "text": "Overview", "bbox": [212, 406, 52, 9], "conf": 0.9929423928260803, "approxSizePx": 6}, {"id": "texts.t24", "text": "Match Details", "bbox": [300, 406, 77, 9], "conf": 0.9901279509067535, "approxSizePx": 6}, {"id": "texts.t25", "text": "Map Zones", "bbox": [413, 406, 62, 10], "conf": 0.9229185283184052, "approxSizePx": 7}, {"id": "texts.t26", "text": "2D Replay PRO", "bbox": [510, 406, 90, 11], "conf": 0.9306292533874512, "approxSizePx": 8}, {"id": "texts.t27", "text": "Add Labels", "bbox": [967, 406, 54, 11], "conf": 0.9668068885803223, "approxSizePx": 8}, {"id": "texts.t28", "text": "Open in CS : GO", "bbox": [1085, 406, 71, 10], "conf": 0.9593291997909545, "approxSizePx": 7}, {"id": "texts.t29", "text": "Get Demo", "bbox": [1212, 407, 49, 8], "conf": 0.9798896014690399, "approxSizePx": 6}, {"id": "texts.t30", "text": "Share Match", "bbox": [1316, 407, 60, 7], "conf": 0.9913085997104645, "approxSizePx": 5}, {"id": "texts.t31", "text": "Practice Servers", "bbox": [46, 420, 84, 8], "conf": 0.989198625087738, "approxSizePx": 6}, {"id": "texts.t32", "text": "3RD", "bbox": [1109, 470, 17, 7], "conf": 0.9821131825447083, "approxSizePx": 5}, {"id": "texts.t33", "text": "2ND", "bbox": [706, 471, 17, 5], "conf": 0.9414150714874268, "approxSizePx": 4}, {"id": "texts.t34", "text": "+ Team Finder", "bbox": [28, 475, 84, 10], "conf": 0.8298870722452799, "approxSizePx": 7}, {"id": "texts.t35", "text": "+5.38", "bbox": [934, 480, 31, 15], "conf": 0.8946084976196289, "approxSizePx": 10}, {"id": "texts.t36", "text": "+1.38", "bbox": [1343, 483, 30, 11], "conf": 0.919489324092865, "approxSizePx": 8}, {"id": "texts.t37", "text": "+6.38", "bbox": [526, 484, 31, 9], "conf": 0.9334326982498169, "approxSizePx": 6}, {"id": "texts.t38", "text": "Player 1", "bbox": [282, 487, 67, 21], "conf": 0.9858621954917908, "approxSizePx": 15}, {"id": "texts.t39", "text": "Player 3", "bbox": [1092, 487, 72, 21], "conf": 0.9868116676807404, "approxSizePx": 15}, {"id": "texts.t40", "text": "Player 2", "bbox": [689, 488, 71, 19], "conf": 0.9844128787517548, "approxSizePx": 13}, {"id": "texts.t41", "text": "* Your Pro", "bbox": [23, 521, 67, 10], "conf": 0.7659431000550588, "approxSizePx": 7}, {"id": "texts.t42", "text": "K / D Ratio", "bbox": [804, 554, 52, 11], "conf": 0.941887155175209, "approxSizePx": 8}, {"id": "texts.t43", "text": "Utility", "bbox": [1264, 554, 31, 12], "conf": 0.987217128276825, "approxSizePx": 8}, {"id": "texts.t44", "text": "Leetify Rating", "bbox": [493, 555, 76, 11], "conf": 0.9817852973937988, "approxSizePx": 8}, {"id": "texts.t45", "text": "My Team", "bbox": [210, 556, 50, 10], "conf": 0.9744769632816315, "approxSizePx": 7}, {"id": "texts.t46", "text": "HLTV Rating", "bbox": [647, 556, 65, 10], "conf": 0.982731431722641, "approxSizePx": 7}, {"id": "texts.t47", "text": "✡", "bbox": [762, 556, 9, 8], "conf": 0.3288725018501282, "approxSizePx": 6}, {"id": "texts.t48", "text": "ADR", "bbox": [956, 556, 23, 8], "conf": 0.9913183450698853, "approxSizePx": 6}, {"id": "texts.t49", "text": "Aim", "bbox": [1108, 556, 21, 8], "conf": 0.9842605590820312, "approxSizePx": 6}, {"id": "texts.t50", "text": "Esports Center", "bbox": [45, 574, 79, 13], "conf": 0.9842564165592194, "approxSizePx": 9}, {"id": "texts.t51", "text": "Player 17", "bbox": [309, 592, 69, 12], "conf": 0.9063088297843933, "approxSizePx": 8}, {"id": "texts.t52", "text": "+6.38 ⭑", "bbox": [493, 592, 51, 11], "conf": 0.58063143491745, "approxSizePx": 8}, {"id": "texts.t53", "text": "1.38⭑", "bbox": [649, 592, 43, 10], "conf": 0.8165869116783142, "approxSizePx": 7}, {"id": "texts.t54", "text": "1.61", "bbox": [804, 593, 24, 9], "conf": 0.9461004734039307, "approxSizePx": 6}, {"id": "texts.t55", "text": "1.61⭑", "bbox": [1110, 593, 44, 11], "conf": 0.835734486579895, "approxSizePx": 8}, {"id": "texts.t56", "text": "115", "bbox": [956, 594, 20, 8], "conf": 0.9794145226478577, "approxSizePx": 6}, {"id": "texts.t57", "text": "102", "bbox": [1264, 594, 19, 8], "conf": 0.9899431467056274, "approxSizePx": 6}, {"id": "texts.t58", "text": "Player 2 T", "bbox": [309, 637, 68, 12], "conf": 0.8493287762006124, "approxSizePx": 8}, {"id": "texts.t59", "text": "118⭑", "bbox": [956, 637, 42, 10], "conf": 0.825481653213501, "approxSizePx": 7}, {"id": "texts.t60", "text": "109⭑", "bbox": [1263, 637, 42, 11], "conf": 0.837167501449585, "approxSizePx": 8}, {"id": "texts.t61", "text": "1.43", "bbox": [804, 638, 24, 9], "conf": 0.9208794832229614, "approxSizePx": 6}, {"id": "texts.t62", "text": "+5.38", "bbox": [494, 639, 30, 8], "conf": 0.9204639196395874, "approxSizePx": 6}, {"id": "texts.t63", "text": "1.11", "bbox": [649, 639, 22, 8], "conf": 0.9439287781715393, "approxSizePx": 6}, {"id": "texts.t64", "text": "1.43", "bbox": [1111, 639, 22, 9], "conf": 0.9487499594688416, "approxSizePx": 6}, {"id": "texts.t65", "text": "Player 3 47", "bbox": [309, 682, 69, 13], "conf": 0.8364204168319702, "approxSizePx": 9}, {"id": "texts.t66", "text": "+1.38", "bbox": [494, 682, 30, 11], "conf": 0.9247087240219116, "approxSizePx": 8}, {"id": "texts.t67", "text": "1.03", "bbox": [649, 684, 23, 9], "conf": 0.9761426448822021, "approxSizePx": 6}, {"id": "texts.t68", "text": "1.32", "bbox": [805, 684, 22, 8], "conf": 0.9705548286437988, "approxSizePx": 6}, {"id": "texts.t69", "text": "99", "bbox": [956, 684, 13, 7], "conf": 0.9739009141921997, "approxSizePx": 5}, {"id": "texts.t70", "text": "1.32", "bbox": [1111, 684, 22, 8], "conf": 0.9595037698745728, "approxSizePx": 6}, {"id": "texts.t71", "text": "99", "bbox": [1263, 684, 13, 7], "conf": 0.977358341217041, "approxSizePx": 5}, {"id": "texts.t72", "text": "-2.38", "bbox": [493, 728, 27, 10], "conf": 0.9567579627037048, "approxSizePx": 7}, {"id": "texts.t73", "text": "0.95", "bbox": [648, 728, 24, 9], "conf": 0.9486097693443298, "approxSizePx": 6}, {"id": "texts.t74", "text": "1.30", "bbox": [805, 728, 22, 9], "conf": 0.9540048837661743, "approxSizePx": 6}, {"id": "texts.t75", "text": "Player 4", "bbox": [309, 729, 43, 9], "conf": 0.9880527257919312, "approxSizePx": 6}, {"id": "texts.t76", "text": "91", "bbox": [956, 729, 13, 7], "conf": 0.9712930917739868, "approxSizePx": 5}, {"id": "texts.t77", "text": "1.30", "bbox": [1111, 729, 23, 8], "conf": 0.9554898142814636, "approxSizePx": 6}, {"id": "texts.t78", "text": "91", "bbox": [1264, 729, 12, 7], "conf": 0.9650020003318787, "approxSizePx": 5}, {"id": "texts.t79", "text": "ОУПФУ", "bbox": [14, 771, 129, 15], "conf": 0.5459874272346497, "approxSizePx": 10}, {"id": "texts.t80", "text": "Player 57", "bbox": [309, 771, 69, 12], "conf": 0.8782768845558167, "approxSizePx": 8}, {"id": "texts.t81", "text": "-3.38", "bbox": [494, 772, 27, 9], "conf": 0.9164149165153503, "approxSizePx": 6}, {"id": "texts.t82", "text": "0.89", "bbox": [648, 772, 24, 9], "conf": 0.9578317403793335, "approxSizePx": 6}, {"id": "texts.t83", "text": "1.10", "bbox": [1111, 772, 21, 9], "conf": 0.9725284576416016, "approxSizePx": 6}, {"id": "texts.t84", "text": "1.10", "bbox": [804, 773, 24, 8], "conf": 0.9678775668144226, "approxSizePx": 6}, {"id": "texts.t85", "text": "90", "bbox": [956, 773, 14, 8], "conf": 0.9879285097122192, "approxSizePx": 6}, {"id": "texts.t86", "text": "90", "bbox": [1263, 773, 15, 9], "conf": 0.9803860783576965, "approxSizePx": 6}, {"id": "texts.t87", "text": "HLTV Rating", "bbox": [647, 813, 65, 13], "conf": 0.9837104976177216, "approxSizePx": 9}, {"id": "texts.t88", "text": "K / D Ratio", "bbox": [804, 814, 52, 10], "conf": 0.9429784417152405, "approxSizePx": 7}, {"id": "texts.t89", "text": "Enemy Team", "bbox": [210, 815, 72, 11], "conf": 0.9889810979366302, "approxSizePx": 8}, {"id": "texts.t90", "text": "ADR", "bbox": [956, 815, 22, 8], "conf": 0.9875195622444153, "approxSizePx": 6}, {"id": "texts.t91", "text": "Aim", "bbox": [1108, 815, 21, 8], "conf": 0.9769878387451172, "approxSizePx": 6}, {"id": "texts.t92", "text": "。 Utility", "bbox": [1223, 815, 71, 11], "conf": 0.7510966062545776, "approxSizePx": 8}, {"id": "texts.t93", "text": "。", "bbox": [1375, 815, 10, 8], "conf": 0.5925671458244324, "approxSizePx": 6}, {"id": "texts.t94", "text": "。", "bbox": [455, 816, 9, 9], "conf": 0.6062580943107605, "approxSizePx": 6}, {"id": "texts.t95", "text": "Leetify Rating", "bbox": [493, 816, 75, 10], "conf": 0.9903949797153473, "approxSizePx": 7}, {"id": "texts.t96", "text": "°", "bbox": [762, 816, 9, 8], "conf": 0.3842296004295349, "approxSizePx": 6}, {"id": "texts.t97", "text": "。", "bbox": [1069, 816, 9, 9], "conf": 0.5368501543998718, "approxSizePx": 6}, {"id": "texts.t98", "text": "Player 6 27", "bbox": [308, 852, 72, 13], "conf": 0.8561393817265829, "approxSizePx": 9}, {"id": "texts.t99", "text": "+4.33", "bbox": [494, 854, 30, 8], "conf": 0.9229225516319275, "approxSizePx": 6}, {"id": "texts.t100", "text": "1.20", "bbox": [649, 854, 23, 8], "conf": 0.9605597853660583, "approxSizePx": 6}, {"id": "texts.t101", "text": "1.23", "bbox": [804, 854, 23, 8], "conf": 0.931160569190979, "approxSizePx": 6}, {"id": "texts.t102", "text": "111", "bbox": [957, 854, 20, 8], "conf": 0.9910856485366821, "approxSizePx": 6}, {"id": "texts.t103", "text": "1.50", "bbox": [1110, 854, 23, 8], "conf": 0.9572432041168213, "approxSizePx": 6}, {"id": "texts.t104", "text": "89", "bbox": [1263, 855, 13, 7], "conf": 0.9626682996749878, "approxSizePx": 5}, {"id": "texts.t105", "text": "Player 7", "bbox": [308, 896, 44, 13], "conf": 0.9908857345581055, "approxSizePx": 9}, {"id": "texts.t106", "text": "+2.45", "bbox": [494, 898, 30, 9], "conf": 0.9289283752441406, "approxSizePx": 6}, {"id": "texts.t107", "text": "1.16", "bbox": [649, 898, 22, 8], "conf": 0.9449608325958252, "approxSizePx": 6}, {"id": "texts.t108", "text": "1.11", "bbox": [805, 898, 22, 9], "conf": 0.9765215516090393, "approxSizePx": 6}, {"id": "texts.t109", "text": "99", "bbox": [956, 898, 14, 7], "conf": 0.9739214181900024, "approxSizePx": 5}, {"id": "texts.t110", "text": "1.20", "bbox": [1110, 898, 23, 8], "conf": 0.9336629509925842, "approxSizePx": 6}, {"id": "texts.t111", "text": "81", "bbox": [1263, 899, 13, 7], "conf": 0.9469701051712036, "approxSizePx": 5}, {"id": "texts.t112", "text": "E", "bbox": [218, 934, 20, 18], "conf": 0.8184860944747925, "approxSizePx": 13}, {"id": "texts.t113", "text": "Player 8", "bbox": [309, 942, 41, 11], "conf": 0.989094614982605, "approxSizePx": 8}, {"id": "texts.t114", "text": "+1.38", "bbox": [494, 943, 29, 8], "conf": 0.9165986180305481, "approxSizePx": 6}, {"id": "texts.t115", "text": "1.02", "bbox": [649, 943, 23, 8], "conf": 0.9561529159545898, "approxSizePx": 6}, {"id": "texts.t116", "text": "0.52", "bbox": [804, 943, 23, 8], "conf": 0.9690219163894653, "approxSizePx": 6}, {"id": "texts.t117", "text": "70", "bbox": [956, 943, 15, 8], "conf": 0.9901278018951416, "approxSizePx": 6}, {"id": "texts.t118", "text": "0.52", "bbox": [1109, 943, 25, 8], "conf": 0.9539986848831177, "approxSizePx": 6}, {"id": "texts.t119", "text": "46", "bbox": [1263, 943, 13, 7], "conf": 0.9791513681411743, "approxSizePx": 5}, {"id": "texts.t120", "text": "Player 97", "bbox": [309, 986, 70, 13], "conf": 0.870435506105423, "approxSizePx": 9}, {"id": "texts.t121", "text": "+0.40", "bbox": [494, 986, 29, 11], "conf": 0.9220743179321289, "approxSizePx": 8}, {"id": "texts.t122", "text": "0.98", "bbox": [648, 988, 23, 9], "conf": 0.9717600345611572, "approxSizePx": 6}, {"id": "texts.t123", "text": "50", "bbox": [957, 988, 12, 8], "conf": 0.9841098785400391, "approxSizePx": 6}, {"id": "texts.t124", "text": "39", "bbox": [1263, 988, 13, 8], "conf": 0.9734970927238464, "approxSizePx": 6}, {"id": "texts.t125", "text": "0.48", "bbox": [804, 989, 23, 8], "conf": 0.9132534861564636, "approxSizePx": 6}, {"id": "texts.t126", "text": "0.48", "bbox": [1110, 989, 22, 8], "conf": 0.9241362810134888, "approxSizePx": 6}, {"id": "texts.t127", "text": "Player 10", "bbox": [309, 1031, 49, 12], "conf": 0.9902560114860535, "approxSizePx": 8}, {"id": "texts.t128", "text": "0.41", "bbox": [1110, 1031, 22, 10], "conf": 0.9428468942642212, "approxSizePx": 7}, {"id": "texts.t129", "text": "-5.50", "bbox": [493, 1032, 28, 9], "conf": 0.9647356271743774, "approxSizePx": 6}, {"id": "texts.t130", "text": "0.80", "bbox": [648, 1032, 24, 9], "conf": 0.9536110758781433, "approxSizePx": 6}, {"id": "texts.t131", "text": "36", "bbox": [1264, 1032, 13, 9], "conf": 0.9883022308349609, "approxSizePx": 6}, {"id": "texts.t132", "text": "0.41", "bbox": [804, 1033, 23, 8], "conf": 0.9017671346664429, "approxSizePx": 6}, {"id": "texts.t133", "text": "36", "bbox": [956, 1033, 15, 8], "conf": 0.9881969094276428, "approxSizePx": 6}], "contrast": [{"id": "contrast.c0", "textId": "texts.t0", "ratio": 18.245, "wcag": "PASS"}, {"id": "contrast.c1", "textId": "texts.t1", "ratio": 4.191, "wcag": "WARN"}, {"id": "contrast.c2", "textId": "texts.t5", "ratio": 18.7, "wcag": "PASS"}, {"id": "contrast.c3", "textId": "texts.t7", "ratio": 18.277, "wcag": "PASS"}, {"id": "contrast.c4", "textId": "texts.t8", "ratio": 18.356, "wcag": "PASS"}, {"id": "contrast.c5", "textId": "texts.t9", "ratio": 19.809, "wcag": "PASS"}, {"id": "contrast.c6", "textId": "texts.t10", "ratio": 19.256, "wcag": "PASS"}, {"id": "contrast.c7", "textId": "texts.t11", "ratio": 19.283, "wcag": "PASS"}, {"id": "contrast.c8", "textId": "texts.t14", "ratio": 7.047, "wcag": "PASS"}, {"id": "contrast.c9", "textId": "texts.t15", "ratio": 6.811, "wcag": "PASS"}, {"id": "contrast.c10", "textId": "texts.t16", "ratio": 6.863, "wcag": "PASS"}, {"id": "contrast.c11", "textId": "texts.t26", "ratio": 8.436, "wcag": "PASS"}, {"id": "contrast.c12", "textId": "texts.t38", "ratio": 18.185, "wcag": "PASS"}, {"id": "contrast.c13", "textId": "texts.t39", "ratio": 18.134, "wcag": "PASS"}, {"id": "contrast.c14", "textId": "texts.t40", "ratio": 18.897, "wcag": "PASS"}, {"id": "contrast.c15", "textId": "texts.t50", "ratio": 15.747, "wcag": "PASS"}, {"id": "contrast.c16", "textId": "texts.t65", "ratio": 11.925, "wcag": "PASS"}, {"id": "contrast.c17", "textId": "texts.t79", "ratio": 17.892, "wcag": "PASS"}, {"id": "contrast.c18", "textId": "texts.t87", "ratio": 14.0, "wcag": "PASS"}, {"id": "contrast.c19", "textId": "texts.t98", "ratio": 11.995, "wcag": "PASS"}, {"id": "contrast.c20", "textId": "texts.t120", "ratio": 12.127, "wcag": "PASS"}], "blocks": [{"id": "blocks.b0", "bbox": [0, 0, 1440, 1097], "kind": "section"}, {"id": "blocks.b1", "bbox": [333, 15, 246, 13], "kind": "unknown"}, {"id": "blocks.b2", "bbox": [212, 96, 162, 28], "kind": "unknown"}, {"id": "blocks.b3", "bbox": [439, 455, 63, 73], "kind": "unknown"}, {"id": "blocks.b4", "bbox": [843, 457, 71, 71], "kind": "unknown"}, {"id": "blocks.b5", "bbox": [1268, 458, 53, 70], "kind": "unknown"}, {"id": "blocks.b6", "bbox": [211, 459, 60, 59], "kind": "unknown"}, {"id": "blocks.b7", "bbox": [619, 459, 59, 58], "kind": "unknown"}, {"id": "blocks.b8", "bbox": [1022, 459, 59, 58], "kind": "unknown"}], "grid": {"cols": 4, "gutterPx": 152, "confidence": 0.11428571428571428}, "buttons": [{"id": "buttons.btn0", "bbox": [1138, 5, 73, 33], "cornerRadius": 1, "hasCenterText": true, "textId": "texts.t2"}, {"id": "buttons.btn1", "bbox": [212, 96, 162, 28], "cornerRadius": 1, "hasCenterText": true, "textId": "texts.t5"}], "palette": {"dominant": ["#1C1B21", "#AB8889", "#292530", "#DFDCDC", "#585C5A"], "mode": "dark"}, "metrics": {"medianVSpace": 0, "leftEdgeVariancePx": 154358.26}, "source": {"ocr": "google:ok", "cv": "opencv-4.10.0", "google": {"client_email": "zombify-vision@zombify-464722.iam.gserviceaccount.com", "project_id": "zombify-464722"}, "debug": {"mode": "file", "path": "/Users/nicholas/.secrets/zombify/vision-key.json", "project_id": "zombify-464722", "client_email": "zombify-vision@zombify-464722.iam.gserviceaccount.com", "has_quota_project": true}, "ocr_exception": null}}